{
    "Stage1Tutorials" : [
        {
            "id": "Welcome",
            "text": "ようこそ！まずは基本操作について覚えよう！"
        },
        {
            "id": "Battle_1",
            "text": "まずバトルについて説明する。\nプレイヤーの行動は左から順番におこなわれる。\n各プレイヤーキャラにエフェクトが表示されたら、\nそのキャラのターン開始となる。"
        },
        {
            "id": "Battle_2",
            "text": "プレイヤーキャラが右のキャラまで行動したら、\n敵のターンになる。"
        },
        {
            "id": "Battle_3",
            "text": "最終的にどちらかが全滅したら、ゲームは終了となる。"
        },
        {
            "id": "Operation_1",
            "text": "次に操作について説明する。\n左下に操作は書かれている。操作はキーボードとマウスで行う。"
        },
        {
            "id": "Operation_2",
            "text": "Aキーを押すと通常攻撃。Sキーを押すと\nスキル攻撃となる。また、Fキーを押すと必殺となる。"
        },
        {
            "id": "Operation_3",
            "text": "必殺とスキルは一度使うと、\nしばらく使えなくなるから、\nステージ2では注意しよう！！"
        },
        {
            "id": "Operation_4",
            "text": "プレイヤーはどの敵に攻撃するか選択でき、\n選択したら敵の上にＵＩが表示される。\n状況を考えて、ターゲットを選択して戦おう！"
        },
        {
            "id": "Status_1",
            "text": "次にステータスについて説明する。\nプレイヤーキャラには様々な役割を持ったキャラがいる。"
        },
        {
            "id": "Status_2",
            "text": "たとえば、攻撃を得意としたアタッカー、\n仲間の強化を得意としたバッファー、\n回復を得意としたヒーラーなど\n様々な役割を持ったキャラがいる。"
        },
        {
            "id": "Status_3",
            "text": "様々な能力キャラのスキルを有効活用して敵を倒そう！！"
        },
        {
            "id": "Status_4",
            "text": "現在のHP状況や攻撃力を確認するには、\n右下の剣のボタンを押すことで確認することができる。\n覚えておこう！"
        },
        {
            "id": "End",
            "text": "これでチュートリアルは終了だ。\nスキルを駆使してクリアを目指そう！！\nそれでは試しに実践と行こう！"
        }
    ]
}